Workbook

Sheet 觀察清單
A1: 市場 | B1: 代號 | C1: 名稱 | D1: 主題 | E1: 子題 | F1: 角色 | G1: 用途 | H1: 評分模型 | I1: 理由 | J1: 保留(Y/N)
A2: 美股 | B2: MRVL | C2: Marvell | D2: 半導體 | E2: 晶片/IC 設計 | F2: 二線 | G2: 候選 | H2: 一般 | I2: 客製 ASIC、光通訊 DSP | J2: Y
A3: 美股 | B3: ALAB | C3: Astera Labs | D3: 半導體 | E3: 晶片/IC 設計 | F3: 二線 | G3: 候選 | H3: 一般 | I3: AI 伺服器連接晶片 | J3: Y
A4: 美股 | B4: CRDO | C4: Credo | D4: 半導體 | E4: 晶片/IC 設計 | F4: 二線 | G4: 候選 | H4: 一般 | I4: 高速傳輸 AEC 線材晶片 | J4: Y
A5: 美股 | B5: ONTO | C5: Onto Innovation | D5: 半導體 | E5: 設備/材料 | F5: 二線 | G5: 候選 | H5: 一般 | I5: 先進封裝檢測 | J5: Y
A6: 美股 | B6: CAMT | C6: Camtek | D6: 半導體 | E6: 設備/材料 | F6: 二線 | G6: 候選 | H6: 一般 | I6: HBM/先進封裝檢測 | J6: Y
A7: 美股 | B7: NVMI | C7: Nova | D7: 半導體 | E7: 設備/材料 | F7: 二線 | G7: 候選 | H7: 一般 | I7: 量測設備 | J7: Y
A8: 美股 | B8: AEHR | C8: Aehr Test | D8: 半導體 | E8: 設備/材料 | F8: 小型潛力 | G8: 候選 | H8: 一般 | I8: 晶圓級燒機測試，股本小 | J8: Y
A9: 美股 | B9: FORM | C9: FormFactor | D9: 半導體 | E9: 設備/材料 | F9: 二線 | G9: 候選 | H9: 一般 | I9: 探針卡，HBM 測試 | J9: Y
A10: 美股 | B10: UCTT | C10: Ultra Clean | D10: 半導體 | E10: 設備/材料 | F10: 小型潛力 | G10: 候選 | H10: 一般 | I10: 設備零組件 | J10: Y
A11: 美股 | B11: AMKR | C11: Amkor | D11: 半導體 | E11: 先進封裝/測試 | F11: 二線 | G11: 候選 | H11: 一般 | I11: 美國最大封測廠 | J11: Y
A12: 台股 | B12: 2408 | C12: 南亞科 | D12: 半導體 | E12: 記憶體 | F12: 龍頭 | G12: 候選 | H12: 一般 | I12: 台灣 DRAM 代表，報價敏感度高 | J12: Y
... A147: 美股 | B147: LLY | C147: 禮來 | D147: 生技 | E147: 減重/代謝 | F147: 龍頭 | G147: 指標 | H147: 生技 | I147: 超大型；減重藥指標 | J147: Y

Sheet 主題摘要
A1: 主題 | B1: 候選-美股 | C1: 候選-台股 | D1: 候選合計 | E1: 其中小型潛力 | F1: 指標股
A2: 半導體 | B2: =COUNTIFS(觀察清單!$D$2:$D$147,$A2,觀察清單!$A$2:$A$147,"美股",觀察清單!$G$2:$G$147,"候選",觀察清單!$J$2:$J$147,"Y") | C2: =COUNTIFS(觀察清單!$D$2:$D$147,$A2,觀察清單!$A$2:$A$147,"台股",觀察清單!$G$2:$G$147,"候選",觀察清單!$J$2:$J$147,"Y") | D2: =B2+C2 | E2: =COUNTIFS(觀察清單!$D$2:$D$147,$A2,觀察清單!$G$2:$G$147,"候選",觀察清單!$F$2:$F$147,"小型潛力",觀察清單!$J$2:$J$147,"Y") | F2: =COUNTIFS(觀察清單!$D$2:$D$147,$A2,觀察清單!$G$2:$G$147,"指標",觀察清單!$J$2:$J$147,"Y")
A3: AI 基建 | B3: =COUNTIFS(觀察清單!$D$2:$D$147,$A3,觀察清單!$A$2:$A$147,"美股",觀察清單!$G$2:$G$147,"候選",觀察清單!$J$2:$J$147,"Y") | C3: =COUNTIFS(觀察清單!$D$2:$D$147,$A3,觀察清單!$A$2:$A$147,"台股",觀察清單!$G$2:$G$147,"候選",觀察清單!$J$2:$J$147,"Y") | D3: =B3+C3 | E3: =COUNTIFS(觀察清單!$D$2:$D$147,$A3,觀察清單!$G$2:$G$147,"候選",觀察清單!$F$2:$F$147,"小型潛力",觀察清單!$J$2:$J$147,"Y") | F3: =COUNTIFS(觀察清單!$D$2:$D$147,$A3,觀察清單!$G$2:$G$147,"指標",觀察清單!$J$2:$J$147,"Y")
A4: 電力 | B4: =COUNTIFS(觀察清單!$D$2:$D$147,$A4,觀察清單!$A$2:$A$147,"美股",觀察清單!$G$2:$G$147,"候選",觀察清單!$J$2:$J$147,"Y") | C4: =COUNTIFS(觀察清單!$D$2:$D$147,$A4,觀察清單!$A$2:$A$147,"台股",觀察清單!$G$2:$G$147,"候選",觀察清單!$J$2:$J$147,"Y") | D4: =B4+C4 | E4: =COUNTIFS(觀察清單!$D$2:$D$147,$A4,觀察清單!$G$2:$G$147,"候選",觀察清單!$F$2:$F$147,"小型潛力",觀察清單!$J$2:$J$147,"Y") | F4: =COUNTIFS(觀察清單!$D$2:$D$147,$A4,觀察清單!$G$2:$G$147,"指標",觀察清單!$J$2:$J$147,"Y")
A5: 機器人 | B5: =COUNTIFS(觀察清單!$D$2:$D$147,$A5,觀察清單!$A$2:$A$147,"美股",觀察清單!$G$2:$G$147,"候選",觀察清單!$J$2:$J$147,"Y") | C5: =COUNTIFS(觀察清單!$D$2:$D$147,$A5,觀察清單!$A$2:$A$147,"台股",觀察清單!$G$2:$G$147,"候選",觀察清單!$J$2:$J$147,"Y") | D5: =B5+C5 | E5: =COUNTIFS(觀察清單!$D$2:$D$147,$A5,觀察清單!$G$2:$G$147,"候選",觀察清單!$F$2:$F$147,"小型潛力",觀察清單!$J$2:$J$147,"Y") | F5: =COUNTIFS(觀察清單!$D$2:$D$147,$A5,觀察清單!$G$2:$G$147,"指標",觀察清單!$J$2:$J$147,"Y")
A6: 生技 | B6: =COUNTIFS(觀察清單!$D$2:$D$147,$A6,觀察清單!$A$2:$A$147,"美股",觀察清單!$G$2:$G$147,"候選",觀察清單!$J$2:$J$147,"Y") | C6: =COUNTIFS(觀察清單!$D$2:$D$147,$A6,觀察清單!$A$2:$A$147,"台股",觀察清單!$G$2:$G$147,"候選",觀察清單!$J$2:$J$147,"Y") | D6: =B6+C6 | E6: =COUNTIFS(觀察清單!$D$2:$D$147,$A6,觀察清單!$G$2:$G$147,"候選",觀察清單!$F$2:$F$147,"小型潛力",觀察清單!$J$2:$J$147,"Y") | F6: =COUNTIFS(觀察清單!$D$2:$D$147,$A6,觀察清單!$G$2:$G$147,"指標",觀察清單!$J$2:$J$147,"Y")
A7: 其他新興（雷達） | B7: =COUNTIFS(觀察清單!$D$2:$D$147,$A7,觀察清單!$A$2:$A$147,"美股",觀察清單!$G$2:$G$147,"候選",觀察清單!$J$2:$J$147,"Y") | C7: =COUNTIFS(觀察清單!$D$2:$D$147,$A7,觀察清單!$A$2:$A$147,"台股",觀察清單!$G$2:$G$147,"候選",觀察清單!$J$2:$J$147,"Y") | D7: =B7+C7 | E7: =COUNTIFS(觀察清單!$D$2:$D$147,$A7,觀察清單!$G$2:$G$147,"候選",觀察清單!$F$2:$F$147,"小型潛力",觀察清單!$J$2:$J$147,"Y") | F7: =COUNTIFS(觀察清單!$D$2:$D$147,$A7,觀察清單!$G$2:$G$147,"指標",觀察清單!$J$2:$J$147,"Y")
A8: 合計 | B8: =SUM(B2:B7) | C8: =SUM(C2:C7) | D8: =SUM(D2:D7) | E8: =SUM(E2:E7) | F8: =SUM(F2:F7)

Sheet 刪除紀錄
A1: 市場 | B1: 代號 | C1: 名稱 | D1: 主題 | E1: 子題 | F1: 角色 | G1: 刪除原因
A2: 台股 | B2: 8271 | C2: 宇瞻 | D2: 半導體 | E2: 記憶體 | F2: 小型潛力 | G2: 純模組廠，只有週期沒有結構成長
A3: 台股 | B3: 2451 | C3: 創見 | D3: 半導體 | E3: 記憶體 | F3: 二線 | G3: 成熟模組廠、成長性低，十倍機率極低
A4: 台股 | B4: 5351 | C4: 鈺創 | D4: 半導體 | E4: 記憶體 | F4: 小型潛力 | G4: 基本面長期疲弱
A5: 台股 | B5: 6770 | C5: 力積電 | D5: 半導體 | E5: 記憶體 | F5: 二線 | G5: 長期虧損、成熟製程受中國競爭壓價
A6: 美股 | B6: ACMR | C6: 盛美 | D6: 半導體 | E6: 設備/材料 | F6: 小型潛力 | G6: 中國曝險與監管風險高
A7: 美股 | B7: KLIC | C7: 庫力索法 | D7: 半導體 | E7: 設備/材料 | F7: 二線 | G7: 成熟週期設備
A8: 美股 | B8: ICHR | C8: Ichor | D8: 半導體 | E8: 設備/材料 | F8: 小型潛力 | G8: 毛利低、客戶集中
A9: 台股 | B9: 6196 | C9: 帆宣 | D9: 半導體 | E9: 設備/材料 | F9: 二線 | G9: 工程承攬、毛利低、成長靠單一客戶資本支出
A10: 美股 | B10: SMCI | C10: 美超微 | D10: AI 基建 | E10: 伺服器/網通 | F10: 二線 | G10: 財報/治理疑慮、毛利被壓縮
A11: 台股 | B11: 2356 | C11: 英業達 | D11: AI 基建 | E11: 伺服器/網通 | F11: 二線 | G11: 低毛利組裝廠
A12: 台股 | B12: 2376 | C12: 技嘉 | D12: AI 基建 | E12: 伺服器/網通 | F12: 二線 | G12: 低毛利、題材性為主
... A40: 美股 | B40: IONQ | C40: IonQ | D40: 其他新興（雷達） | E40: 量子運算 | F40: 小型潛力 | G40: 自由現金流殖利率 -1.9%（為負，2026-10 依新規則刪除；改回 Y 即恢復追蹤）

Sheet 說明
A1: 篩選邏輯（v2）
A2: 候選 | B2: 真正拿來評分、找十倍股的標的
A3: 指標 | B3: 市值太大、十倍幾乎不可能，但它們發動代表產業啟動，用來觸發『產業鏈擴散』掃描二線小型股
A4: 刪除 | B4: 有明顯紅旗：長期虧損、嚴重稀釋、治理疑慮、成長停滯、資產擴張遠快於獲利（研究中的負面指標）。原因見『刪除紀錄』，日後條件改善可加回
A5: 重要 | B5: 這是依產業地位與已知基本面的質化判斷，不是計算出來的機率；真正的機率分數由追蹤器用即時資料計算
A6: 重要 | B6: 判斷基於 2026 年中以前的資訊，之後的新發展可能沒反映到
A7: 保留(Y/N) | B7: 黃底欄位，改 N 即不追蹤
A8: 注意 | B8: 這是追蹤池，不是買進建議
